pywolai/__init__.py
pywolai/api.py
pywolai/block.py
pywolai/block_format.py
pywolai/enums/__init__.py
pywolai/enums/block_align.py
pywolai/enums/block_back_colors.py
pywolai/enums/block_front_colors.py
pywolai/enums/block_type.py
pywolai/enums/error_code.py
pywolai/enums/inline_title_type.py
pywolai/enums/rich_text.py
pywolai/enums/text_align.py
pywolai-0.1.0.dist-info/METADATA
pywolai-0.1.0.dist-info/WHEEL
pywolai-0.1.0.dist-info/top_level.txt
pywolai-0.1.0.dist-info/RECORD
