Metadata-Version: 2.1
Name: pywolai
Version: 0.1.0
Summary: Python wrapper for wolai API
Author: xuzhougeng
Author-email: xuzhougeng@163.com
Requires-Dist: requests
